{
  "generated_utc": "2026-04-27T12:00:05Z",
  "horizon_min": 60,
  "sites": [
    {
      "site": "Angliss Hospital",
      "network": "Eastern Health",
      "latest_obs_utc": "2026-04-27T12:00:01Z",
      "waiting_count": 20,
      "current_wait_min": 65.0,
      "max_wait_min": 241,
      "predicted_wait_min": 65.0,
      "wait_momentum": 0.0,
      "confidence": 0.832,
      "confidence_label": "High",
      "ctx_source": "VAHI",
      "color": "red",
      "heartbeat_age_mins": 0.1,
      "strain_index": 1.25
    },
    {
      "site": "Maroondah Hospital",
      "network": "Eastern Health",
      "latest_obs_utc": "2026-04-27T12:00:01Z",
      "waiting_count": 25,
      "current_wait_min": 79.0,
      "max_wait_min": 228,
      "predicted_wait_min": 113.4,
      "wait_momentum": 17.2,
      "confidence": 0.576,
      "confidence_label": "Moderate",
      "ctx_source": "VAHI",
      "color": "red",
      "heartbeat_age_mins": 0.1,
      "strain_index": 1.829
    },
    {
      "site": "Box Hill Hospital",
      "network": "Eastern Health",
      "latest_obs_utc": "2026-04-27T12:00:01Z",
      "waiting_count": 48,
      "current_wait_min": 51.0,
      "max_wait_min": 243,
      "predicted_wait_min": 71.2,
      "wait_momentum": 10.1,
      "confidence": 0.674,
      "confidence_label": "Moderate",
      "ctx_source": "VAHI",
      "color": "red",
      "heartbeat_age_mins": 0.1,
      "strain_index": 0.8
    },
    {
      "site": "Monash Medical Centre - Clayton",
      "network": "Monash Health",
      "latest_obs_utc": "2026-04-27T12:00:01Z",
      "waiting_count": 40,
      "current_wait_min": 58.0,
      "max_wait_min": 342,
      "predicted_wait_min": 94.4,
      "wait_momentum": 18.2,
      "confidence": 0.493,
      "confidence_label": "Moderate",
      "ctx_source": "VAHI",
      "color": "red",
      "heartbeat_age_mins": 0.1,
      "strain_index": 3.045
    },
    {
      "site": "Casey Hospital",
      "network": "Monash Health",
      "latest_obs_utc": "2026-04-27T12:00:01Z",
      "waiting_count": 23,
      "current_wait_min": 54.0,
      "max_wait_min": 335,
      "predicted_wait_min": 54.0,
      "wait_momentum": 0.0,
      "confidence": 0.664,
      "confidence_label": "Moderate",
      "ctx_source": "VAHI",
      "color": "amber",
      "heartbeat_age_mins": 0.1,
      "strain_index": 1.8
    },
    {
      "site": "Dandenong Hospital",
      "network": "Monash Health",
      "latest_obs_utc": "2026-04-27T12:00:01Z",
      "waiting_count": 23,
      "current_wait_min": 37.0,
      "max_wait_min": 166,
      "predicted_wait_min": 37.0,
      "wait_momentum": 0.0,
      "confidence": 0.683,
      "confidence_label": "Moderate",
      "ctx_source": "VAHI",
      "color": "amber",
      "heartbeat_age_mins": 0.1,
      "strain_index": 1.85
    }
  ]
}