{
  "generated_utc": "2026-04-27T08:05:51Z",
  "horizon_min": 60,
  "sites": [
    {
      "site": "Angliss Hospital",
      "network": "Eastern Health",
      "latest_obs_utc": "2026-04-27T08:00:03Z",
      "current_wait_min": 52.0,
      "max_wait_min": 202,
      "predicted_wait_min": 108.6,
      "wait_momentum": 28.3,
      "confidence": 0.599,
      "confidence_label": "Moderate",
      "ctx_source": "VAHI",
      "color": "red",
      "heartbeat_age_mins": 5.8,
      "strain_index": 2.088
    },
    {
      "site": "Maroondah Hospital",
      "network": "Eastern Health",
      "latest_obs_utc": "2026-04-27T08:00:03Z",
      "current_wait_min": 30.0,
      "max_wait_min": 163,
      "predicted_wait_min": 56.2,
      "wait_momentum": 13.1,
      "confidence": 0.672,
      "confidence_label": "Moderate",
      "ctx_source": "VAHI",
      "color": "amber",
      "heartbeat_age_mins": 5.8,
      "strain_index": 0.906
    },
    {
      "site": "Box Hill Hospital",
      "network": "Eastern Health",
      "latest_obs_utc": "2026-04-27T08:00:03Z",
      "current_wait_min": 18.0,
      "max_wait_min": 253,
      "predicted_wait_min": 18.0,
      "wait_momentum": 0.0,
      "confidence": 0.775,
      "confidence_label": "High",
      "ctx_source": "VAHI",
      "color": "green",
      "heartbeat_age_mins": 5.8,
      "strain_index": 0.202
    },
    {
      "site": "Monash Medical Centre - Clayton",
      "network": "Monash Health",
      "latest_obs_utc": "2026-04-27T07:30:03Z",
      "current_wait_min": 60.0,
      "max_wait_min": 174,
      "predicted_wait_min": 62.0,
      "wait_momentum": 1.0,
      "confidence": 0.652,
      "confidence_label": "Moderate",
      "ctx_source": "VAHI",
      "color": "red",
      "heartbeat_age_mins": 35.8,
      "strain_index": 2.0
    },
    {
      "site": "Casey Hospital",
      "network": "Monash Health",
      "latest_obs_utc": "2026-04-27T07:30:03Z",
      "current_wait_min": 43.0,
      "max_wait_min": 146,
      "predicted_wait_min": 41.0,
      "wait_momentum": -1.0,
      "confidence": 0.727,
      "confidence_label": "High",
      "ctx_source": "VAHI",
      "color": "amber",
      "heartbeat_age_mins": 35.8,
      "strain_index": 1.367
    },
    {
      "site": "Dandenong Hospital",
      "network": "Monash Health",
      "latest_obs_utc": "2026-04-27T07:30:03Z",
      "current_wait_min": 33.0,
      "max_wait_min": 77,
      "predicted_wait_min": 31.8,
      "wait_momentum": -0.6,
      "confidence": 0.717,
      "confidence_label": "High",
      "ctx_source": "VAHI",
      "color": "amber",
      "heartbeat_age_mins": 35.8,
      "strain_index": 1.59
    }
  ]
}